migrations/0001_initial.py
migrations/__init__.py
models/__init__.py
models/allergens_model.py
models/combo_ingredients_model.py
models/combo_ingredients_section_model.py
models/combo_sections_model.py
models/combos_model.py
models/custom_users_model.py
models/extra_ingredients_model.py
models/products_model.py
models/removable_ingredients_model.py
models/restaurant_categories_model.py
models/restaurants_model.py
dishify.database-0.1.dist-info/METADATA
dishify.database-0.1.dist-info/WHEEL
dishify.database-0.1.dist-info/top_level.txt
dishify.database-0.1.dist-info/RECORD
